lantern/__init__.py
lantern/score.py
lantern/util.py
lantern/analysis/__init__.py
lantern/analysis/frequency.py
lantern/analysis/search.py
lantern/analysis/english_ngrams/__init__.py
lantern/analysis/english_ngrams/bigrams.py
lantern/analysis/english_ngrams/quadgrams.py
lantern/analysis/english_ngrams/trigrams.py
lantern/analysis/english_ngrams/unigrams.py
lantern/fitness/__init__.py
lantern/fitness/chisquared.py
lantern/fitness/corpus.py
lantern/fitness/ngram.py
lantern/fitness/patternmatch.py
lantern/modules/__init__.py
lantern/modules/caesar.py
lantern/modules/simplesubstitution.py
lantern/modules/vigenere.py
lantern/structures/__init__.py
lantern/structures/decryption.py
lantern/structures/dynamicdict.py
lantern-0.1.0.dist-info/DESCRIPTION.rst
lantern-0.1.0.dist-info/METADATA
lantern-0.1.0.dist-info/RECORD
lantern-0.1.0.dist-info/WHEEL
lantern-0.1.0.dist-info/metadata.json
lantern-0.1.0.dist-info/top_level.txt
