Metadata-Version: 2.0
Name: lantern
Version: 0.1.0
Summary: Automated Cryptanalysis
Home-page: https://github.com/CameronLonsdale/lantern
Author: Cameron Lonsdale
Author-email: cameron.lonsdale@gmail.com
License: MIT
Platform: UNKNOWN
